iot_message/__init__.py
iot_message/crypt.py
iot_message/exception.py
iot_message/factory.py
iot_message/message.py
iot_message/abstract/__init__.py
iot_message/abstract/cryptor_interface.py
iot_message/cryptor/__init__.py
iot_message/cryptor/aes_sha1.py
iot_message/cryptor/base64.py
iot_message/cryptor/plain.py
iot_message-1.2.1.dist-info/LICENSE
iot_message-1.2.1.dist-info/METADATA
iot_message-1.2.1.dist-info/WHEEL
iot_message-1.2.1.dist-info/top_level.txt
iot_message-1.2.1.dist-info/RECORD
