Metadata-Version: 2.1
Name: iot-message
Version: 1.2.1
Summary: Custom iot:1 protocol
Home-page: https://github.com/bkosciow/python_iot-1
Author: Bartosz Kościów
Author-email: kosci1@gmail.com
License: MIT
Keywords: iot:1
Platform: UNKNOWN
Classifier: Development Status :: 4 - Beta
Classifier: Environment :: Console
Classifier: Intended Audience :: Developers
Classifier: Natural Language :: English
Classifier: License :: OSI Approved :: MIT License
Classifier: Operating System :: OS Independent
Classifier: Programming Language :: Python
Classifier: Programming Language :: Python :: 3
Classifier: Topic :: Software Development :: Libraries :: Python Modules
Classifier: Topic :: Home Automation
